colast/__init__.py
colast/colast.py
colast/py.typed
colast-0.1.2.dist-info/METADATA
colast-0.1.2.dist-info/WHEEL
colast-0.1.2.dist-info/licenses/LICENSE
colast-0.1.2.dist-info/RECORD
