Metadata-Version: 2.4
Name: colast
Version: 0.1.2
Summary: Utilities that assist development workflows on Google Colab
Project-URL: Homepage, https://github.com/dd-n-kk/colast
Project-URL: Documentation, https://colast.readthedocs.io
Project-URL: Issues, https://github.com/dd-n-kk/colast/issues
Author-email: dd-n-kk <djlstvn.cs03@gmail.com>
License-File: LICENSE
Keywords: Colab,GitHub,Google,cloud,uv,workflow
Classifier: Intended Audience :: Developers
Classifier: License :: OSI Approved :: MIT License
Classifier: Programming Language :: Python :: 3
Classifier: Topic :: Utilities
Requires-Python: <3.12,>=3.10
